LICENSE
README.md
setup.py
prefect_postgres_sensors/__init__.py
prefect_postgres_sensors.egg-info/PKG-INFO
prefect_postgres_sensors.egg-info/SOURCES.txt
prefect_postgres_sensors.egg-info/dependency_links.txt
prefect_postgres_sensors.egg-info/requires.txt
prefect_postgres_sensors.egg-info/top_level.txt