Metadata-Version: 2.1
Name: prefect-postgres-sensors
Version: 0.6.0
Summary: Prefect sensors for monitoring PostgreSQL databases
Home-page: UNKNOWN
Author: James-Wachuka
Author-email: jewachu26@email.com
License: UNKNOWN
Platform: UNKNOWN
License-File: LICENSE
